{"response_code":0,"results":[{"category":"Entertainment: Television","type":"boolean","difficulty":"medium","question":"AMC&#039;s &quot;The Walking Dead&quot;, Rick, Carl, Daryl, Morgan, Carol and Maggie were introduced to us in Season 1.","correct_answer":"False","incorrect_answers":["True"]},{"category":"General Knowledge","type":"multiple","difficulty":"easy","question":"Virgin Trains, Virgin Atlantic and Virgin Racing, are all companies owned by which famous entrepreneur?   ","correct_answer":"Richard Branson","incorrect_answers":["Alan Sugar","Donald Trump","Bill Gates"]},{"category":"History","type":"boolean","difficulty":"easy","question":"The Cold War ended with Joseph Stalin&#039;s death.","correct_answer":"False","incorrect_answers":["True"]},{"category":"History","type":"boolean","difficulty":"easy","question":"The Tiananmen Square protests of 1989 were held in Hong Kong.","correct_answer":"False","incorrect_answers":["True"]},{"category":"Entertainment: Music","type":"multiple","difficulty":"easy","question":"Ringo Starr of The Beatles mainly played what instrument?","correct_answer":"Drums","incorrect_answers":["Bass","Guitar","Piano"]},{"category":"Sports","type":"multiple","difficulty":"easy","question":"Which team won the 2015-16 English Premier League?","correct_answer":"Leicester City","incorrect_answers":["Liverpool","Cheslea","Manchester United"]},{"category":"Entertainment: Video Games","type":"multiple","difficulty":"easy","question":"Who is the main character of the game Half-Life: Opposing Force?","correct_answer":"Adrian Shephard","incorrect_answers":["Gordon Freeman","Alyx Vance","Barney Calhoun"]},{"category":"Sports","type":"multiple","difficulty":"medium","question":"Which Formula One driver was nicknamed &#039;The Professor&#039;?","correct_answer":"Alain Prost","incorrect_answers":["Ayrton Senna","Niki Lauda","Emerson Fittipaldi"]},{"category":"Geography","type":"multiple","difficulty":"easy","question":"What colour is the circle on the Japanese flag?","correct_answer":"Red","incorrect_answers":["White","Yellow","Black"]},{"category":"Entertainment: Board Games","type":"boolean","difficulty":"medium","question":"In the game &quot;Racko&quot; you may pick up ANY card from the discard pile.","correct_answer":"False","incorrect_answers":["True"]},{"category":"Science: Computers","type":"multiple","difficulty":"easy","question":"The series of the Intel HD graphics generation succeeding that of the 5000 and 6000 series (Broadwell) is called:","correct_answer":"HD Graphics 500","incorrect_answers":["HD Graphics 700 ","HD Graphics 600","HD Graphics 7000"]},{"category":"History","type":"multiple","difficulty":"medium","question":"According to scholarly estimates, what percentage of the world population at the time died due to Tamerlane&#039;s conquests?","correct_answer":"5%","incorrect_answers":["1%","3%","&lt;1%"]},{"category":"Entertainment: Video Games","type":"boolean","difficulty":"easy","question":"There are 6 legendary cards in &quot;Clash Royale&quot;.","correct_answer":"False","incorrect_answers":["True"]},{"category":"Entertainment: Video Games","type":"multiple","difficulty":"easy","question":"Which eSports team came first place in The International Dota 2 Championship 2016?","correct_answer":"Wings Gaming","incorrect_answers":["Digital Chaos","Evil Geniuses","Fnatic"]},{"category":"Entertainment: Video Games","type":"multiple","difficulty":"hard","question":"When was the first &quot;Half-Life&quot; released?","correct_answer":"1998","incorrect_answers":["2004","1999","1997"]},{"category":"Entertainment: Video Games","type":"boolean","difficulty":"easy","question":"In Kingdom Hearts the Paopu fruit is said to intertwine the destinies for two people forever.","correct_answer":"True","incorrect_answers":["False"]},{"category":"Entertainment: Film","type":"multiple","difficulty":"hard","question":"What did the first moving picture depict?","correct_answer":"A galloping horse","incorrect_answers":["A woman in a dress","A man walking","A crackling fire"]},{"category":"Entertainment: Music","type":"multiple","difficulty":"medium","question":"Who is the lead singer of Silverchair?","correct_answer":"Daniel Johns","incorrect_answers":["Ben Gillies","Chris Joannou","George Costanza"]},{"category":"Science: Computers","type":"multiple","difficulty":"medium","question":"What does the acronym CDN stand for in terms of networking?","correct_answer":"Content Delivery Network","incorrect_answers":["Content Distribution Network","Computational Data Network","Compressed Data Network"]},{"category":"Entertainment: Video Games","type":"multiple","difficulty":"medium","question":"Which of these is the name of a cut enemy from &quot;Half-Life 2&quot;?","correct_answer":"Hydra","incorrect_answers":["Cthulu","Spike","Tremor"]},{"category":"Entertainment: Japanese Anime & Manga","type":"multiple","difficulty":"medium","question":"The main protagonist of the fifth part of JoJo&#039;s Bizarre Adventure is which of the following?","correct_answer":"Giorno Giovanna","incorrect_answers":["Guido Mista","Jonathan Joestar","Joey JoJo"]},{"category":"Vehicles","type":"multiple","difficulty":"medium","question":"Which supercar company is from Sweden?","correct_answer":"Koenigsegg","incorrect_answers":["Bugatti","Lamborghini","McLaren"]},{"category":"Entertainment: Japanese Anime & Manga","type":"boolean","difficulty":"medium","question":"The anime Attack on Titan was directed by Tetsur\u014d Araki, the same person who directed the anime Highschool of the Dead.","correct_answer":"True","incorrect_answers":["False"]},{"category":"Science: Computers","type":"multiple","difficulty":"medium","question":"What is the name of the default theme that is installed with Windows XP?","correct_answer":"Luna","incorrect_answers":["Neptune","Whistler","Bliss"]},{"category":"Entertainment: Film","type":"multiple","difficulty":"medium","question":"Who played Sgt. Gordon Elias in &#039;Platoon&#039; (1986)?","correct_answer":"Willem Dafoe","incorrect_answers":["Charlie Sheen","Matt Damon","Johnny Depp"]},{"category":"History","type":"boolean","difficulty":"medium","question":"The Hundred Years&#039; War was fought for more than a hundred years.","correct_answer":"True","incorrect_answers":["False"]},{"category":"Vehicles","type":"boolean","difficulty":"medium","question":"Bugatti was an Italian car manufacturer.","correct_answer":"False","incorrect_answers":["True"]},{"category":"Animals","type":"multiple","difficulty":"medium","question":"What dog bread is one of the oldest breeds of dog and has flourished since before 400 BCE.","correct_answer":"Pugs","incorrect_answers":["Bulldogs","Boxers","Chihuahua"]},{"category":"Entertainment: Video Games","type":"boolean","difficulty":"medium","question":"David Baszucki was a co-founder of ROBLOX Corporation.","correct_answer":"True","incorrect_answers":["False"]},{"category":"History","type":"multiple","difficulty":"medium","question":"The Fallingwater House, located in Pennsylvania, was designed by which architect?","correct_answer":"Frank Lloyd Wright","incorrect_answers":["Antoni Gaudi","Frank Gehry","Le Corbusier"]},{"category":"General Knowledge","type":"multiple","difficulty":"easy","question":"What was the first ever London Underground line to be built?","correct_answer":"Metropolitan Line","incorrect_answers":["Circle Line","Bakerloo Line","Victoria Line"]},{"category":"Entertainment: Comics","type":"multiple","difficulty":"medium","question":"In the comics, which Sonic character took command of the Dark Legion after Luger&#039;s assassination?","correct_answer":"Lien-Da","incorrect_answers":["Kragok","Dimitri","Remington"]},{"category":"Entertainment: Music","type":"multiple","difficulty":"easy","question":"Which classical composer wrote the &quot;Moonlight Sonata&quot;?","correct_answer":"Ludvig Van Beethoven","incorrect_answers":["Chief Keef","Wolfgang Amadeus Mozart","Johannes Brahms"]},{"category":"Entertainment: Video Games","type":"multiple","difficulty":"hard","question":"In &quot;The Binding of Isaac&quot;, which item instantly kills Mom and Mom&#039;s Heart?","correct_answer":"The Bible","incorrect_answers":["The Halo","Brimstone","Book of Shadows"]},{"category":"Entertainment: Film","type":"multiple","difficulty":"medium","question":"Mark Wahlberg played the titular character of which 2008 video-game adaptation?","correct_answer":"Max Payne","incorrect_answers":["Alan Wake","Hitman","God Of War"]},{"category":"Science & Nature","type":"boolean","difficulty":"medium","question":"Pneumonoultramicroscopicsilicovolcanoconiosis is a synonym for the disease known as silicosis.","correct_answer":"True","incorrect_answers":["False"]},{"category":"Entertainment: Television","type":"multiple","difficulty":"medium","question":"In &quot;The Simpsons&quot;, what is the real name of &quot;Comic Book Guy&quot;?","correct_answer":"Jeff Albertson","incorrect_answers":["Comic Book Guy","Edward Stone","Jack Richardson"]},{"category":"Entertainment: Board Games","type":"multiple","difficulty":"hard","question":"In Magic: The Gathering, which of the following was the first publicly released foil card?","correct_answer":"Lightning Dragon","incorrect_answers":["Revenant","Beast of Burden","Dirtcowl Wurm"]},{"category":"Entertainment: Music","type":"multiple","difficulty":"hard","question":"What was the name of the rock band that Nobuo Uematsu formed that played songs from various Final Fantasy games?","correct_answer":"The Black Mages","incorrect_answers":["The Final Fantasies","The Espers","The Rock Summoners"]},{"category":"History","type":"multiple","difficulty":"medium","question":"When did construction of the Suez Canal finish?","correct_answer":"1869","incorrect_answers":["1859","1860","1850"]},{"category":"General Knowledge","type":"multiple","difficulty":"hard","question":"Where is Apple Inc. headquartered?","correct_answer":"Cupertino, California","incorrect_answers":["Redwood City, California","Redmond, Washington","Santa Monica, CA"]},{"category":"Entertainment: Music","type":"boolean","difficulty":"medium","question":"A Facebook campaign placed Rage Against The Machine&#039;s &quot;Killing in the Name Of&quot; as the UK Christmas Number 1 in 2009.","correct_answer":"True","incorrect_answers":["False"]},{"category":"Entertainment: Japanese Anime & Manga","type":"boolean","difficulty":"hard","question":"The character Plum from &quot;No Game No Life&quot; is a girl.","correct_answer":"False","incorrect_answers":["True"]},{"category":"General Knowledge","type":"boolean","difficulty":"easy","question":"Slovakia is a member of European Union-","correct_answer":"True","incorrect_answers":["False"]},{"category":"Entertainment: Video Games","type":"boolean","difficulty":"easy","question":"There are 2 player roles in Trouble in Terrorist Town.","correct_answer":"False","incorrect_answers":["True"]},{"category":"Entertainment: Video Games","type":"multiple","difficulty":"medium","question":"The mobile game &quot;Jetpack Joyride&quot; was released in what year? ","correct_answer":"2011","incorrect_answers":["2012","2009","2014"]},{"category":"General Knowledge","type":"multiple","difficulty":"easy","question":"When was the Playstation 3 released?","correct_answer":"November 11, 2006","incorrect_answers":["January 8, 2007","December 25, 2007","July 16, 2006"]},{"category":"Entertainment: Video Games","type":"multiple","difficulty":"hard","question":"In the game Enter the Gungeon, which one of these is not a playable character?","correct_answer":"The Wizard","incorrect_answers":["The Bullet","The Robot","The Cultist"]},{"category":"General Knowledge","type":"multiple","difficulty":"easy","question":"In aerodynamics, which force pushes an object upwards?","correct_answer":"Lift","incorrect_answers":["Drag","Weight","Thrust"]},{"category":"General Knowledge","type":"multiple","difficulty":"hard","question":"In &quot;Resident Evil 3&quot;, how many inventory slots does Jill have at the start of the game?","correct_answer":"10","incorrect_answers":["6","8","12"]}]}